{".class": "MypyFile", "_fullname": "django.contrib.sites.models", "is_partial_stub_package": false, "is_stub": true, "names": {".class": "SymbolTable", "Any": {".class": "SymbolTableNode", "cross_ref": "typing.Any", "kind": "Gdef", "module_hidden": true, "module_public": false}, "HttpRequest": {".class": "SymbolTableNode", "cross_ref": "django.http.request.HttpRequest", "kind": "Gdef", "module_hidden": true, "module_public": false}, "Optional": {".class": "SymbolTableNode", "cross_ref": "typing.Optional", "kind": "Gdef", "module_hidden": true, "module_public": false}, "SITE_CACHE": {".class": "SymbolTableNode", "kind": "Gdef", "node": {".class": "Var", "flags": ["is_ready"], "fullname": "django.contrib.sites.models.SITE_CACHE", "name": "SITE_CACHE", "type": {".class": "AnyType", "missing_import_name": null, "source_any": null, "type_of_any": 2}}}, "Site": {".class": "SymbolTableNode", "kind": "Gdef", "node": {".class": "TypeInfo", "_promote": null, "abstract_attributes": [], "bases": ["django.db.models.base.Model"], "declared_metaclass": null, "defn": {".class": "ClassDef", "fullname": "django.contrib.sites.models.Site", "name": "Site", "type_vars": []}, "flags": [], "fullname": "django.contrib.sites.models.Site", "metaclass_type": "django.db.models.base.ModelBase", "metadata": {}, "module_name": "django.contrib.sites.models", "mro": ["django.contrib.sites.models.Site", "django.db.models.base.Model", "builtins.object"], "names": {".class": "SymbolTable", "domain": {".class": "SymbolTableNode", "kind": "Mdef", "node": {".class": "Var", "flags": ["is_initialized_in_class"], "fullname": "django.contrib.sites.models.Site.domain", "name": "domain", "type": {".class": "Instance", "args": [{".class": "AnyType", "missing_import_name": null, "source_any": null, "type_of_any": 5}, {".class": "AnyType", "missing_import_name": null, "source_any": null, "type_of_any": 5}], "type_ref": "django.db.models.fields.CharField"}}}, "name": {".class": "SymbolTableNode", "kind": "Mdef", "node": {".class": "Var", "flags": ["is_initialized_in_class"], "fullname": "django.contrib.sites.models.Site.name", "name": "name", "type": {".class": "Instance", "args": [{".class": "AnyType", "missing_import_name": null, "source_any": null, "type_of_any": 5}, {".class": "AnyType", "missing_import_name": null, "source_any": null, "type_of_any": 5}], "type_ref": "django.db.models.fields.CharField"}}}, "natural_key": {".class": "SymbolTableNode", "kind": "Mdef", "node": {".class": "FuncDef", "arg_kinds": [0], "arg_names": ["self"], "flags": [], "fullname": "django.contrib.sites.models.Site.natural_key", "name": "natural_key", "type": {".class": "CallableType", "arg_kinds": [0], "arg_names": ["self"], "arg_types": ["django.contrib.sites.models.Site"], "bound_args": [], "def_extras": {"first_arg": "self"}, "fallback": "builtins.function", "implicit": false, "is_ellipsis_args": false, "name": "natural_key of Site", "ret_type": {".class": "TupleType", "implicit": false, "items": ["builtins.str"], "partial_fallback": {".class": "Instance", "args": [{".class": "AnyType", "missing_import_name": null, "source_any": null, "type_of_any": 6}], "type_ref": "builtins.tuple"}}, "variables": []}}}, "objects": {".class": "SymbolTableNode", "kind": "Mdef", "node": {".class": "Var", "flags": ["is_initialized_in_class", "is_ready"], "fullname": "django.contrib.sites.models.Site.objects", "name": "objects", "type": "django.contrib.sites.models.SiteManager"}}}, "tuple_type": null, "type_vars": [], "typeddict_type": null}}, "SiteManager": {".class": "SymbolTableNode", "kind": "Gdef", "node": {".class": "TypeInfo", "_promote": null, "abstract_attributes": [], "bases": [{".class": "Instance", "args": ["django.contrib.sites.models.Site"], "type_ref": "django.db.models.manager.Manager"}], "declared_metaclass": null, "defn": {".class": "ClassDef", "fullname": "django.contrib.sites.models.SiteManager", "name": "SiteManager", "type_vars": []}, "flags": [], "fullname": "django.contrib.sites.models.SiteManager", "metaclass_type": "abc.ABCMeta", "metadata": {}, "module_name": "django.contrib.sites.models", "mro": ["django.contrib.sites.models.SiteManager", "django.db.models.manager.Manager", "django.db.models.manager.BaseManager", "django.db.models.query.QuerySet", "django.db.models.query._BaseQuerySet", "typing.Collection", "typing.Iterable", "typing.Container", "typing.Reversible", "typing.Sized", "builtins.object"], "names": {".class": "SymbolTable", "clear_cache": {".class": "SymbolTableNode", "kind": "Mdef", "node": {".class": "FuncDef", "arg_kinds": [0], "arg_names": ["self"], "flags": [], "fullname": "django.contrib.sites.models.SiteManager.clear_cache", "name": "clear_cache", "type": {".class": "CallableType", "arg_kinds": [0], "arg_names": ["self"], "arg_types": ["django.contrib.sites.models.SiteManager"], "bound_args": [], "def_extras": {"first_arg": "self"}, "fallback": "builtins.function", "implicit": false, "is_ellipsis_args": false, "name": "clear_cache of SiteManager", "ret_type": {".class": "NoneType"}, "variables": []}}}, "get_by_natural_key": {".class": "SymbolTableNode", "kind": "Mdef", "node": {".class": "FuncDef", "arg_kinds": [0, 0], "arg_names": ["self", "domain"], "flags": [], "fullname": "django.contrib.sites.models.SiteManager.get_by_natural_key", "name": "get_by_natural_key", "type": {".class": "CallableType", "arg_kinds": [0, 0], "arg_names": ["self", "domain"], "arg_types": ["django.contrib.sites.models.SiteManager", "builtins.str"], "bound_args": [], "def_extras": {"first_arg": "self"}, "fallback": "builtins.function", "implicit": false, "is_ellipsis_args": false, "name": "get_by_natural_key of SiteManager", "ret_type": "django.contrib.sites.models.Site", "variables": []}}}, "get_current": {".class": "SymbolTableNode", "kind": "Mdef", "node": {".class": "FuncDef", "arg_kinds": [0, 1], "arg_names": ["self", "request"], "flags": [], "fullname": "django.contrib.sites.models.SiteManager.get_current", "name": "get_current", "type": {".class": "CallableType", "arg_kinds": [0, 1], "arg_names": ["self", "request"], "arg_types": ["django.contrib.sites.models.SiteManager", {".class": "UnionType", "items": ["django.http.request.HttpRequest", {".class": "NoneType"}]}], "bound_args": [], "def_extras": {"first_arg": "self"}, "fallback": "builtins.function", "implicit": false, "is_ellipsis_args": false, "name": "get_current of SiteManager", "ret_type": "django.contrib.sites.models.Site", "variables": []}}}}, "tuple_type": null, "type_vars": [], "typeddict_type": null}}, "Tuple": {".class": "SymbolTableNode", "cross_ref": "typing.Tuple", "kind": "Gdef", "module_hidden": true, "module_public": false}, "Type": {".class": "SymbolTableNode", "cross_ref": "typing.Type", "kind": "Gdef", "module_hidden": true, "module_public": false}, "__doc__": {".class": "SymbolTableNode", "kind": "Gdef", "node": {".class": "Var", "flags": ["is_ready"], "fullname": "django.contrib.sites.models.__doc__", "name": "__doc__", "type": "builtins.str"}}, "__file__": {".class": "SymbolTableNode", "kind": "Gdef", "node": {".class": "Var", "flags": ["is_ready"], "fullname": "django.contrib.sites.models.__file__", "name": "__file__", "type": "builtins.str"}}, "__name__": {".class": "SymbolTableNode", "kind": "Gdef", "node": {".class": "Var", "flags": ["is_ready"], "fullname": "django.contrib.sites.models.__name__", "name": "__name__", "type": "builtins.str"}}, "__package__": {".class": "SymbolTableNode", "kind": "Gdef", "node": {".class": "Var", "flags": ["is_ready"], "fullname": "django.contrib.sites.models.__package__", "name": "__package__", "type": "builtins.str"}}, "clear_site_cache": {".class": "SymbolTableNode", "kind": "Gdef", "node": {".class": "FuncDef", "arg_kinds": [0, 4], "arg_names": ["sender", "kwargs"], "flags": [], "fullname": "django.contrib.sites.models.clear_site_cache", "name": "clear_site_cache", "type": {".class": "CallableType", "arg_kinds": [0, 4], "arg_names": ["sender", "kwargs"], "arg_types": [{".class": "TypeType", "item": "django.contrib.sites.models.Site"}, {".class": "AnyType", "missing_import_name": null, "source_any": null, "type_of_any": 2}], "bound_args": [], "def_extras": {"first_arg": null}, "fallback": "builtins.function", "implicit": false, "is_ellipsis_args": false, "name": "clear_site_cache", "ret_type": {".class": "NoneType"}, "variables": []}}}, "models": {".class": "SymbolTableNode", "cross_ref": "django.db.models", "kind": "Gdef", "module_public": false}}, "path": "/usr/local/Caskroom/miniconda/base/envs/DjangoEnv/lib/python3.8/site-packages/django-stubs/contrib/sites/models.pyi"}